vsc_dm-0.0.1.9733600432.dist-info/entry_points.txt
vsc_dm-0.0.1.9733600432.dist-info/LICENSE
vsc_dm-0.0.1.9733600432.dist-info/WHEEL
vsc_dm-0.0.1.9733600432.dist-info/top_level.txt
vsc_dm-0.0.1.9733600432.dist-info/RECORD
vsc_dm-0.0.1.9733600432.dist-info/METADATA
vsc_dm/__build_num__.py
vsc_dm/core.cpython-310-x86_64-linux-gnu.so
vsc_dm/pkginfo.py
vsc_dm/__init__.py
