Metadata-Version: 2.1
Name: vsc-dm
Version: 0.0.1.9733600432
Summary: Core Verification Stimulus and Coverage library
Home-page: https://github.com/vsc-tools/vsc-dm
Author: Matthew Ballance
Author-email: matt.ballance@gmail.com
License: Apache 2.0
Keywords: SystemVerilog,Verilog,RTL,Python
License-File: LICENSE
Requires-Dist: debug-mgr
